openai_toolchain/__init__.py
openai_toolchain/_version.py
openai_toolchain/client.py
openai_toolchain/py.typed
openai_toolchain/registry.py
openai_toolchain/tools.py
openai_toolchain/types.py
openai_toolchain-0.3.0.dist-info/licenses/LICENSE
openai_toolchain-0.3.0.dist-info/METADATA
openai_toolchain-0.3.0.dist-info/WHEEL
openai_toolchain-0.3.0.dist-info/top_level.txt
openai_toolchain-0.3.0.dist-info/RECORD
